README
setup.py
imager/__init__.py
imager/arguments.py
imager/executable.py
imager/imaging.py
imager/info.py
imager/logger.py
imager/notifier.py
imager/novafunctions.py
imager/prefabs.py
imager/strings.py
imager/systemconfig.py
imager/utils.py
xenosimager.egg-info/PKG-INFO
xenosimager.egg-info/SOURCES.txt
xenosimager.egg-info/dependency_links.txt
xenosimager.egg-info/entry_points.txt
xenosimager.egg-info/requires.txt
xenosimager.egg-info/top_level.txt