Metadata-Version: 1.0
Name: xenosimager
Version: 0.003
Summary: Create an image of a instance from data obtained from within the instance
Home-page: http://github.com/cloudnull/transporter
Author: Kevin Carter
Author-email: kevin.carter@rackspace.com
License: Apache2.0
Platform: UNKNOWN
Classifier: Intended Audience :: Information Technology
Classifier: Intended Audience :: System Administrators
Classifier: Intended Audience :: Developers
Classifier: Operating System :: OS Independent
Classifier: Programming Language :: Python :: 2.6
Classifier: Programming Language :: Python :: 2.7
Classifier: Topic :: Utilities
Classifier: Topic :: Software Development :: Libraries :: Python Modules
